COPYING
MANIFEST.in
README.rst
development.txt
requirements.txt
setup.cfg
setup.py
docs/Makefile
docs/make.bat
docs/source/api.rst
docs/source/conf.py
docs/source/index.rst
p4rr0t007/__init__.py
p4rr0t007/settings.py
p4rr0t007/version.py
p4rr0t007/web.py
p4rr0t007.egg-info/PKG-INFO
p4rr0t007.egg-info/SOURCES.txt
p4rr0t007.egg-info/dependency_links.txt
p4rr0t007.egg-info/not-zip-safe
p4rr0t007.egg-info/requires.txt
p4rr0t007.egg-info/top_level.txt
p4rr0t007/lib/__init__.py
p4rr0t007/lib/core.py
p4rr0t007/lib/http.py
p4rr0t007/lib/l33t.py
p4rr0t007/lib/local.py
p4rr0t007/lib/mailing.py
p4rr0t007/lib/tr4nsl33t0r.py