Metadata-Version: 1.0
Name: p4rr0t007
Version: 0.3.10
Summary: h1gh lEv3l fl4sk 4 h4x0rs
Home-page: https://github.com/c0ntrol-x/p4rr0t007
Author: Ð4√¡η¢Ч
Author-email: d4v1ncy@protonmail.ch
License: UNKNOWN
Platform: UNKNOWN
